<?xml version="1.0" encoding="utf-8"?>
<optionset Name="tc_app" localizedName="App" xmlns:xsi="http://www.w3.org/2001/XMLSchema-instance">
  <OptionSetType>picklist</OptionSetType>
  <IsGlobal>1</IsGlobal>
  <IntroducedVersion>1.7.0.0</IntroducedVersion>
  <IsCustomizable>1</IsCustomizable>
  <ExternalTypeName></ExternalTypeName>
  <displaynames>
    <displayname description="App" languagecode="1033" />
  </displaynames>
  <Descriptions>
    <Description description="" languagecode="1033" />
  </Descriptions>
  <options>
    <option value="948010000" ExternalValue="" Color="">
      <labels>
        <label description="SCEM" languagecode="1033" />
      </labels>
      <Descriptions>
        <Description description="" languagecode="1033" />
      </Descriptions>
    </option>
    <option value="948010001" ExternalValue="" Color="">
      <labels>
        <label description="OPP" languagecode="1033" />
      </labels>
      <Descriptions>
        <Description description="" languagecode="1033" />
      </Descriptions>
    </option>
    <option value="948010002" ExternalValue="" Color="">
      <labels>
        <label description="IEC" languagecode="1033" />
      </labels>
      <Descriptions>
        <Description description="" languagecode="1033" />
      </Descriptions>
    </option>
    <option value="948010003" ExternalValue="" Color="#0000ff">
      <labels>
        <label description="Rail Safety" languagecode="1033" />
      </labels>
      <Descriptions>
        <Description description="" languagecode="1033" />
      </Descriptions>
    </option>
    <option value="948010004" ExternalValue="" Color="#0000ff">
      <labels>
        <label description="TDG Secretariat" languagecode="1033" />
      </labels>
      <Descriptions>
        <Description description="" languagecode="1033" />
      </Descriptions>
    </option>
    <option value="948010005" ExternalValue="" Color="#0000ff">
      <labels>
        <label description="Safety Awareness" languagecode="1033" />
      </labels>
      <Descriptions>
        <Description description="" languagecode="1033" />
      </Descriptions>
    </option>
  </options>
</optionset>